ClusterAgent-4.5.dist-info/DESCRIPTION.rst
ClusterAgent-4.5.dist-info/entry_points.txt
ClusterAgent-4.5.dist-info/METADATA
ClusterAgent-4.5.dist-info/metadata.json
ClusterAgent-4.5.dist-info/RECORD
ClusterAgent-4.5.dist-info/top_level.txt
ClusterAgent-4.5.dist-info/WHEEL
cluster_agent/core.py
cluster_agent/infra_http_service.py
cluster_agent/task_excution.py
cluster_agent/__init__.py
cluster_agent/__version__.py
